odoo/addons/sale_quick_blanket_order/README.rst
odoo/addons/sale_quick_blanket_order/__init__.py
odoo/addons/sale_quick_blanket_order/__manifest__.py
odoo/addons/sale_quick_blanket_order/i18n/sale_quick_blanket_order.pot
odoo/addons/sale_quick_blanket_order/models/__init__.py
odoo/addons/sale_quick_blanket_order/models/product_product.py
odoo/addons/sale_quick_blanket_order/models/sale_blanket_order.py
odoo/addons/sale_quick_blanket_order/readme/CONTRIBUTORS.rst
odoo/addons/sale_quick_blanket_order/readme/DESCRIPTION.rst
odoo/addons/sale_quick_blanket_order/readme/USAGE.rst
odoo/addons/sale_quick_blanket_order/static/description/icon.png
odoo/addons/sale_quick_blanket_order/static/description/index.html
odoo/addons/sale_quick_blanket_order/tests/__init__.py
odoo/addons/sale_quick_blanket_order/tests/test_quick_blanket_sale.py
odoo/addons/sale_quick_blanket_order/views/sale_blanket_order_view.xml
odoo14_addon_sale_quick_blanket_order-14.0.1.0.1.dist-info/METADATA
odoo14_addon_sale_quick_blanket_order-14.0.1.0.1.dist-info/WHEEL
odoo14_addon_sale_quick_blanket_order-14.0.1.0.1.dist-info/top_level.txt
odoo14_addon_sale_quick_blanket_order-14.0.1.0.1.dist-info/RECORD
