Metadata-Version: 2.1
Name: odoo14-addon-sale-quick-blanket-order
Version: 14.0.1.0.1
Summary: Quick Sale Blanket Orders
Home-page: https://github.com/OCA/sale-workflow
Author: Odoo Community Association (OCA), PyTech-SRL
Author-email: support@odoo-community.org
License: AGPL-3
Platform: UNKNOWN
Classifier: Programming Language :: Python
Classifier: Framework :: Odoo
Classifier: Framework :: Odoo :: 14.0
Classifier: License :: OSI Approved :: GNU Affero General Public License v3
Requires-Python: >=3.6
Requires-Dist: odoo14-addon-sale-blanket-order
Requires-Dist: odoo14-addon-sale-quick
Requires-Dist: odoo <14.1dev,>=14.0a
